Flask_REST_multiformat_api-0.1.0.dist-info/METADATA
Flask_REST_multiformat_api-0.1.0.dist-info/RECORD
Flask_REST_multiformat_api-0.1.0.dist-info/WHEEL
Flask_REST_multiformat_api-0.1.0.dist-info/top_level.txt
flask_rest_multiformat_api/__init__.py
flask_rest_multiformat_api/api.py
flask_rest_multiformat_api/date_util.py
flask_rest_multiformat_api/errors.py
flask_rest_multiformat_api/exceptions.py
flask_rest_multiformat_api/queries.py
flask_rest_multiformat_api/serialize.py
flask_rest_multiformat_api/utils.py
flask_rest_multiformat_api/view.py
flask_rest_multiformat_api/format/__init__.py
flask_rest_multiformat_api/format/jsonapi.py
flask_rest_multiformat_api/format/simple_json.py
tests/format/__init__.py
tests/format/jsonapi/__init__.py
tests/format/jsonapi/test_parse.py
tests/format/simple_json/__init__.py
tests/format/simple_json/test_parse.py
